{
  "name": "Cyberdeck Salvage",
  "$schema": "vscode://schemas/color-theme",
  "semanticHighlighting": true,
  "colors": {
    "descriptionForeground": "#5a5850",
    "editorWidget.foreground": "#7cc4b8",
    "errorForeground": "#daae6d",
    "focusBorder": "#1a2422",
    "foreground": "#5a5850",
    "icon.foreground": "#daae6d",
    "sash.hoverBorder": "#daae6d",
    "widget.border": "#243230",
    "widget.shadow": "#243230",
    "contrastActiveBorder": "#daae6d",
    "contrastBorder": "#243230",
    "activityBar.activeBackground": "#daae6d33",
    "activityBar.activeBorder": "#daae6d",
    "activityBar.background": "#1a2422",
    "activityBar.border": "#243230",
    "activityBar.inactiveForeground": "#daae6d",
    "activityBarBadge.foreground": "#141c1a",
    "badge.background": "#daae6d",
    "badge.foreground": "#141c1a",
    "breadcrumb.activeSelectionForeground": "#f0ece4",
    "breadcrumb.background": "#1a2422",
    "breadcrumb.focusForeground": "#daae6d",
    "breadcrumb.foreground": "#f0ece499",
    "breadcrumbPicker.background": "#1a2422",
    "button.background": "#daae6d21",
    "button.foreground": "#f0ece4",
    "button.hoverBackground": "#5a5850",
    "debugExceptionWidget.background": "#1a2422",
    "debugExceptionWidget.border": "#f0ece4",
    "debugToolBar.background": "#2a3830",
    "diffEditor.insertedTextBackground": "#4d9e9b26",
    "diffEditor.removedTextBackground": "#daae6d17",
    "dropdown.background": "#1a2422",
    "dropdown.border": "#1a2422",
    "dropdown.foreground": "#5a5850",
    "editor.background": "#1a2422",
    "editor.findMatchBackground": "#2e3e3a",
    "editor.findMatchHighlightBackground": "#2e3e3a87",
    "editor.findRangeHighlightBackground": "#2e3e3a1a",
    "editor.foreground": "#d4d0c8",
    "editor.hoverHighlightBackground": "#2e3e3a4d",
    "editor.inactiveSelectionBackground": "#f0ece433",
    "editor.lineHighlightBackground": "#2e3e3a66",
    "editor.lineHighlightBorder": "#2e3e3a66",
    "editor.rangeHighlightBackground": "#5a585038",
    "editor.selectionBackground": "#3a4e4887",
    "editor.selectionHighlightBackground": "#daae6d33",
    "editor.snippetFinalTabstopHighlightBackground": "#141c1a",
    "editor.snippetFinalTabstopHighlightBorder": "#141c1a",
    "editor.snippetTabstopHighlightBackground": "#141c1a",
    "editor.snippetTabstopHighlightBorder": "#141c1a",
    "editor.wordHighlightBackground": "#2e3e3a87",
    "editor.wordHighlightStrongBackground": "#2e3e3a87",
    "editorBracketMatch.background": "#2e3e3a66",
    "editorCodeLens.foreground": "#f0ece4cc",
    "editorCursor.foreground": "#daae6d",
    "editorError.border": "#1a2422",
    "editorError.foreground": "#daae6d",
    "editorGroup.border": "#243230",
    "editorGroup.dropBackground": "#5a585033",
    "editorGroup.emptyBackground": "#5a585033",
    "editorGroupHeader.noTabsBackground": "#1a2422",
    "editorGroupHeader.tabsBackground": "#1a2422",
    "editorGroupHeader.tabsBorder": "#141c1a",
    "editorGutter.addedBackground": "#1a2e28d6",
    "editorGutter.background": "#1a2422",
    "editorGutter.deletedBackground": "#2e2220a3",
    "editorGutter.modifiedBackground": "#daae6d",
    "editorHint.border": "#4d9e9b00",
    "editorHint.foreground": "#4d9e9b",
    "editorHoverWidget.background": "#141c1a",
    "editorHoverWidget.border": "#243230",
    "editorIndentGuide.activeBackground1": "#243230",
    "editorIndentGuide.background1": "#5a585038",
    "editorInfo.border": "#1a2422",
    "editorInfo.foreground": "#daae6d",
    "editorLineNumber.activeForeground": "#5a5850",
    "editorLineNumber.foreground": "#5a5850",
    "editorLink.activeForeground": "#89e3f6",
    "editorMarkerNavigation.background": "#43435629",
    "editorMarkerNavigationError.background": "#daae6d",
    "editorMarkerNavigationWarning.background": "#daae6d",
    "editorOverviewRuler.addedForeground": "#09f7a099",
    "editorOverviewRuler.border": "#1a2422",
    "editorOverviewRuler.commonContentForeground": "#daae6d45",
    "editorOverviewRuler.currentContentForeground": "#24323045",
    "editorOverviewRuler.deletedForeground": "#daae6d99",
    "editorOverviewRuler.errorForeground": "#2a2220ed",
    "editorOverviewRuler.findMatchForeground": "#2e3e3a87",
    "editorOverviewRuler.incomingContentForeground": "#cac4f545",
    "editorOverviewRuler.modifiedForeground": "#5a585099",
    "editorOverviewRuler.warningForeground": "#daae6dcc",
    "editorRuler.foreground": "#2e3e3a33",
    "editorSuggestWidget.background": "#141c1a",
    "editorSuggestWidget.border": "#243230",
    "editorSuggestWidget.foreground": "#b8b4ac",
    "editorSuggestWidget.highlightForeground": "#daae6d",
    "editorSuggestWidget.selectedBackground": "#2e3e3a",
    "editorWarning.border": "#1a2422",
    "editorWarning.foreground": "#daae6d",
    "editorWhitespace.foreground": "#f0ece421",
    "editorWidget.background": "#1a2422",
    "editorWidget.border": "#243230",
    "extensionButton.prominentBackground": "#daae6d",
    "extensionButton.prominentForeground": "#141c1a",
    "extensionButton.prominentHoverBackground": "#4d9e9b",
    "gitDecoration.addedResourceForeground": "#daae6dcc",
    "gitDecoration.conflictingResourceForeground": "#daae6d",
    "gitDecoration.deletedResourceForeground": "#2a2220ed",
    "gitDecoration.ignoredResourceForeground": "#f0ece459",
    "gitDecoration.modifiedResourceForeground": "#daae6d",
    "gitDecoration.untrackedResourceForeground": "#b8b4ac",
    "input.background": "#141c1a",
    "input.border": "#141c1a",
    "input.foreground": "#9a9690",
    "input.placeholderForeground": "#9a9690",
    "inputOption.activeBorder": "#9a9690",
    "inputValidation.errorBackground": "#daae6d80",
    "inputValidation.errorBorder": "#daae6d00",
    "inputValidation.errorForeground": "#daae6d",
    "inputValidation.infoBackground": "#1a2422",
    "inputValidation.infoBorder": "#4d9e9b",
    "inputValidation.infoForeground": "#daae6d",
    "inputValidation.warningBackground": "#1a2422",
    "inputValidation.warningBorder": "#daae6d",
    "inputValidation.warningForeground": "#daae6d",
    "list.activeSelectionBackground": "#24323080",
    "list.dropBackground": "#2e3e3a66",
    "list.errorForeground": "#daae6de6",
    "list.focusBackground": "#1a2422",
    "list.focusForeground": "#f0ece4",
    "list.highlightForeground": "#daae6d",
    "list.hoverBackground": "#283634",
    "list.inactiveFocusBackground": "#1a2422",
    "list.inactiveSelectionBackground": "#2e3e3a66",
    "list.inactiveSelectionForeground": "#f0ece4",
    "list.warningForeground": "#daae6d",
    "listFilterWidget.background": "#141c1a",
    "listFilterWidget.noMatchesOutline": "#daae6d",
    "listFilterWidget.outline": "#4d9e9b",
    "menu.background": "#1a2422",
    "menu.foreground": "#daae6d",
    "menu.selectionBackground": "#daae6d80",
    "menu.selectionBorder": "#1a2422",
    "menu.selectionForeground": "#daae6d",
    "menu.separatorBackground": "#daae6d",
    "menubar.selectionBackground": "#1a2422",
    "menubar.selectionBorder": "#1a2422",
    "menubar.selectionForeground": "#daae6d",
    "merge.border": "#1a242200",
    "merge.commonContentBackground": "#daae6d21",
    "merge.commonHeaderBackground": "#daae6d45",
    "merge.currentContentBackground": "#24323021",
    "merge.currentHeaderBackground": "#24323045",
    "merge.incomingContentBackground": "#aea8dc21",
    "merge.incomingHeaderBackground": "#aea8dc45",
    "minimap.errorHighlight": "#2a2220ed",
    "minimap.findMatchHighlight": "#daae6ded",
    "minimap.warningHighlight": "#daae6ded",
    "minimapGutter.addedBackground": "#4d9e9b",
    "minimapGutter.deletedBackground": "#daae6d",
    "minimapGutter.modifiedBackground": "#4d9e9b",
    "notificationCenter.border": "#1a2422",
    "notificationCenterHeader.background": "#1a2422",
    "notificationCenterHeader.foreground": "#9a9690",
    "notificationLink.foreground": "#f0ece4",
    "notificationToast.border": "#1a2422",
    "notifications.background": "#1a2422",
    "notifications.border": "#1a2422",
    "notifications.foreground": "#9a9690",
    "panel.background": "#1a2422",
    "panelTitle.inactiveForeground": "#4a4842",
    "peekView.border": "#5a5850",
    "peekViewEditor.background": "#1a2422",
    "peekViewEditor.matchHighlightBackground": "#2e3e3a",
    "peekViewEditor.matchHighlightBorder": "#1a2422",
    "peekViewEditorGutter.background": "#1a2422",
    "peekViewResult.background": "#1a2422",
    "peekViewResult.fileForeground": "#daae6d",
    "peekViewResult.lineForeground": "#f0ece4",
    "peekViewResult.matchHighlightBackground": "#1a2422",
    "peekViewResult.selectionBackground": "#0d181a",
    "peekViewResult.selectionForeground": "#f0ece4",
    "peekViewTitle.background": "#1a2422",
    "peekViewTitleDescription.foreground": "#f0ece4",
    "peekViewTitleLabel.foreground": "#daae6d",
    "pickerGroup.border": "#4d9e9b",
    "pickerGroup.foreground": "#9a9690",
    "progressBar.background": "#daae6d",
    "scrollbar.shadow": "#243230",
    "scrollbarSlider.activeBackground": "#2e3e3a78",
    "scrollbarSlider.background": "#2e3e3a33",
    "scrollbarSlider.hoverBackground": "#2e3e3a54",
    "settings.checkboxBackground": "#1a2422",
    "settings.checkboxBorder": "#1a2422",
    "settings.checkboxForeground": "#5a5850",
    "settings.dropdownBackground": "#1a2422",
    "settings.dropdownBorder": "#1a2422",
    "settings.dropdownForeground": "#5a5850",
    "settings.dropdownListBorder": "#2e3e3a",
    "settings.headerForeground": "#daae6d",
    "settings.modifiedItemIndicator": "#4d9e9b",
    "settings.numberInputBackground": "#141c1a",
    "settings.numberInputBorder": "#141c1a",
    "settings.numberInputForeground": "#9a9690",
    "settings.textInputBackground": "#1a2422",
    "settings.textInputBorder": "#1a2422",
    "settings.textInputForeground": "#5a5850",
    "sideBar.background": "#141c1a",
    "sideBar.border": "#243230",
    "sideBar.dropBackground": "#141c1a",
    "sideBar.foreground": "#9a9690",
    "sideBarSectionHeader.background": "#1a2422",
    "sideBarSectionHeader.border": "#243230",
    "sideBarSectionHeader.foreground": "#89e3f6",
    "sideBarTitle.foreground": "#89e3f6",
    "statusBar.background": "#1a2422",
    "statusBar.border": "#243230",
    "statusBar.debuggingBackground": "#1a2422",
    "statusBar.debuggingBorder": "#08080fb0",
    "statusBar.debuggingForeground": "#7cc4b8",
    "statusBar.foreground": "#89e3f6",
    "statusBar.noFolderBackground": "#1a2422",
    "statusBar.noFolderBorder": "#1a2422",
    "statusBar.noFolderForeground": "#f0ece4",
    "statusBarItem.activeBackground": "#1a242266",
    "statusBarItem.hoverBackground": "#243230",
    "statusBarItem.prominentBackground": "#243230",
    "statusBarItem.prominentHoverBackground": "#2e3e3a",
    "tab.activeBackground": "#1a2422",
    "tab.activeBorderTop": "#1a2422",
    "tab.activeModifiedBorder": "#4d9e9b",
    "tab.border": "#243230",
    "tab.inactiveBackground": "#1a2422",
    "tab.inactiveForeground": "#4a4842",
    "tab.unfocusedActiveBackground": "#181f1d",
    "tab.unfocusedActiveBorder": "#1a2422",
    "tab.unfocusedActiveForeground": "#89e3f6",
    "tab.unfocusedHoverBackground": "#daae6d21",
    "tab.unfocusedInactiveForeground": "#4a4842",
    "terminal.ansiBlack": "#141c1a",
    "terminal.ansiBlue": "#44786a",
    "terminal.ansiBrightBlack": "#4a4842",
    "terminal.ansiBrightBlue": "#5a9890",
    "terminal.ansiBrightCyan": "#a0ecf8",
    "terminal.ansiBrightGreen": "#6eb8b0",
    "terminal.ansiBrightMagenta": "#c898a0",
    "terminal.ansiBrightRed": "#d47060",
    "terminal.ansiBrightWhite": "#f0ece4",
    "terminal.ansiBrightYellow": "#e8c080",
    "terminal.ansiCyan": "#89e3f6",
    "terminal.ansiGreen": "#4d9e9b",
    "terminal.ansiMagenta": "#b08090",
    "terminal.ansiRed": "#c45a4a",
    "terminal.ansiWhite": "#5a5850",
    "terminal.ansiYellow": "#daae6d",
    "terminal.background": "#141c1a",
    "terminalCursor.background": "#141c1a",
    "terminalCursor.foreground": "#daae6d",
    "textBlockQuote.background": "#1a2422",
    "textBlockQuote.border": "#9a9690",
    "textCodeBlock.background": "#1a2422",
    "textLink.activeForeground": "#daae6d",
    "textLink.foreground": "#daae6d",
    "textPreformat.foreground": "#daae6d",
    "textSeparator.foreground": "#1a2422",
    "titleBar.activeBackground": "#1a2422",
    "titleBar.activeForeground": "#daae6d",
    "titleBar.inactiveBackground": "#1a2422",
    "titleBar.inactiveForeground": "#f0ece499",
    "tree.indentGuidesStroke": "#5a5850",
    "walkThrough.embeddedEditorBackground": "#1a2422"
  },
  "semanticTokenColors": {
    "*.abstract": {
      "fontStyle": "italic"
    },
    "*.async": {},
    "*.callable": {},
    "*.consuming": {},
    "*.controlFlow": {},
    "*.crateRoot": {
      "fontStyle": "bold"
    },
    "*.declaration": {},
    "*.defaultLibrary": {},
    "*.definition": {},
    "*.deprecated": {
      "fontStyle": "strikethrough"
    },
    "*.documentation": {
      "fontStyle": "italic"
    },
    "*.injected": {},
    "*.intraDocLink": {
      "fontStyle": "underline"
    },
    "*.library": {},
    "*.modification": {},
    "*.mutable": {
      "fontStyle": "underline"
    },
    "*.public": {},
    "*.readonly": {},
    "*.reference": {},
    "*.static": {},
    "*.trait": {},
    "*.unsafe": {
      "foreground": "#b08090"
    },
    "arithmetic": {
      "foreground": "#daae6d",
      "fontStyle": "bold"
    },
    "attribute": "#d4a060",
    "attributeBracket": "#daae6d",
    "bitwise": {
      "foreground": "#daae6d",
      "fontStyle": "bold"
    },
    "boolean": "#d4a054",
    "brace": "#b08090",
    "bracket": "#b08090",
    "builtinAttribute": "#d4a060",
    "builtinType": "#7cc4b8",
    "character": "#c9856a",
    "class": {
      "foreground": "#4d9e9b",
      "fontStyle": "bold"
    },
    "colon": "#8a8680",
    "comma": "#8a8680",
    "comment": {
      "foreground": "#5a6860",
      "fontStyle": "italic"
    },
    "comparison": {
      "foreground": "#daae6d",
      "fontStyle": "bold"
    },
    "const": "#8f704b",
    "constParameter": "#8f704b",
    "decorator": "#89e3f6",
    "derive": "#d4a060",
    "deriveHelper": "#d4a060",
    "dot": {
      "foreground": "#daae6d",
      "fontStyle": "bold"
    },
    "enum": {
      "foreground": "#4d9e9b",
      "fontStyle": "bold"
    },
    "enumMember": "#8f704b",
    "escapeSequence": {
      "foreground": "#e8b878",
      "fontStyle": "bold"
    },
    "event": "#8f704b",
    "formatSpecifier": "#8f704b",
    "function": "#89e3f6",
    "interface": {
      "foreground": "#4d9e9b",
      "fontStyle": "bold"
    },
    "invalidEscapeSequence": "#c45a4a",
    "keyword": {
      "foreground": "#daae6d",
      "fontStyle": "bold"
    },
    "label": "#b08090",
    "lifetime": "#7cc4b8",
    "logical": {
      "foreground": "#daae6d",
      "fontStyle": "bold"
    },
    "macro": "#b08090",
    "macroBang": "#b08090",
    "method": "#89e3f6",
    "namespace": "#8a80a8",
    "number": "#d4a054",
    "operator": {
      "foreground": "#daae6d",
      "fontStyle": "bold"
    },
    "parameter": {
      "foreground": "#4d9e9b",
      "fontStyle": "bold"
    },
    "parenthesis": "#b08090",
    "procMacro": "#b08090",
    "property": "#6eb8b0",
    "punctuation": "#8a8680",
    "regexp": "#c9856a",
    "selfKeyword": {
      "foreground": "#daae6d",
      "fontStyle": "bold"
    },
    "selfTypeKeyword": {
      "foreground": "#4d9e9b",
      "fontStyle": "bold"
    },
    "semicolon": "#b08090",
    "static": "#8f704b",
    "string": "#c9856a",
    "struct": {
      "foreground": "#4d9e9b",
      "fontStyle": "bold"
    },
    "toolModule": "#d4a060",
    "type": {
      "foreground": "#4d9e9b",
      "fontStyle": "bold"
    },
    "typeAlias": {
      "foreground": "#4d9e9b",
      "fontStyle": "bold"
    },
    "typeParameter": {
      "foreground": "#4d9e9b",
      "fontStyle": "bold"
    },
    "union": {
      "foreground": "#4d9e9b",
      "fontStyle": "bold"
    },
    "unresolvedReference": "#c45a4a",
    "variable": "#4d9e9b"
  },
  "tokenColors": [
    {
      "scope": [
        "abstract.definition.fsharp entity",
        "abstract.definition.fsharp keyword",
        "comment",
        "comment.block.documentation storage.type.class",
        "comment.block.documentation.phpdoc.php keyword",
        "comment.block.documentation.rust",
        "comment.block.documentation.scala keyword",
        "comment.block.documentation.scala variable.parameter",
        "comment.block.javadoc.java keyword",
        "comment.block.javadoc.java variable.parameter.java",
        "comment.block.lua",
        "comment.block.rust",
        "comment.line.documentation.rust",
        "comment.line.double-dash.documentation.lua",
        "comment.line.double-slash.rust",
        "comment.line.roxygen.r keyword",
        "comment.line.roxygen.r variable.parameter.r",
        "constant.other.math",
        "constant.other.placeholder",
        "constant.other.symbol.hashkey.ruby",
        "constant.other.symbol.hashkey.ruby punctuation.definition.constant.ruby",
        "constant.other.symbol.ruby",
        "constant.other.table-name",
        "entity.alias.import.go",
        "entity.name.footnote",
        "entity.name.function.directive.graphql",
        "entity.name.record.field.accessor.elm",
        "entity.name.scope-resolution.function.call",
        "entity.name.type.kotlin",
        "entity.other",
        "function.anonymous keyword",
        "keyword.control.clojure",
        "keyword.control.export",
        "keyword.control.inheritance.coffee",
        "keyword.declaration.enum.rust",
        "keyword.declaration.struct.rust",
        "keyword.declaration.trait.rust",
        "keyword.declaration.type.rust",
        "keyword.function.go",
        "keyword.import",
        "keyword.language.gherkin.feature.step",
        "keyword.operator.documentation.powershell",
        "keyword.other.array.phpdoc.php",
        "keyword.other.base.cs",
        "keyword.other.capture-specifier",
        "keyword.other.import",
        "keyword.other.this.cs",
        "keyword.package",
        "keyword.type.cs",
        "markup.italic",
        "markup.quote",
        "meta.import keyword.control",
        "meta.preprocessor.pragma.nim",
        "punctuation.definition.comment",
        "sharing.modifier",
        "source.apex keyword.type",
        "source.clojure meta.symbol.dynamic",
        "source.go storage.type",
        "source.graphql support.type.enum",
        "source.hlsl storage.type.basic",
        "source.nim storage.type.concrete",
        "source.ocaml entity.name.filename",
        "source.python support.type.python",
        "source.r meta.function.r keyword.control.r",
        "source.reason entity.name.filename",
        "source.scala entity.name.class",
        "source.swift keyword.other.declaration-specifier",
        "source.swift support.type",
        "source.tf meta.keyword.number",
        "source.tf meta.keyword.string",
        "source.vala storage.type.generic",
        "source.wsd keyword.control.diagram",
        "storage.modifier",
        "storage.modifier.mut.rust",
        "storage.modifier.rust",
        "storage.type.built-in",
        "storage.type.core.rust",
        "storage.type.function.kotlin",
        "storage.type.integral",
        "storage.type.modifier",
        "storage.type.php",
        "storage.type.primitive",
        "storage.type.scala",
        "support.class.builtin",
        "support.constant.vendored",
        "support.function.builtin.go",
        "support.function.textit",
        "support.type.builtin",
        "support.type.core.rust",
        "support.type.julia",
        "support.type.primitive",
        "support.type.vendored",
        "support.variable.swift",
        "tag.decorator.js entity.name.tag.js",
        "tag.decorator.js punctuation.definition.tag.js",
        "text.tex support.function.emph",
        "variable.language",
        "variable.other.field",
        "variable.other.member",
        "variable.other.member.c",
        "variable.other.object.property",
        "variable.other.property",
        "variable.other.table.property.lua",
        "variable.parameter.function.language.special"
      ],
      "settings": {
        "fontStyle": "italic"
      }
    },
    {
      "scope": [
        "binding.fsharp keyword",
        "comment.block.documentation punctuation.definition.block.tag",
        "comment.block.documentation punctuation.definition.inline.tag",
        "constant.language.empty-list.haskell",
        "entity.name.function.macro.rules.rust",
        "entity.name.function.macro.rust",
        "entity.name.tag",
        "entity.name.type.macro.rust",
        "entity.tag.apacheconf",
        "function.anonymous keyword",
        "function.anonymous keyword.symbol.fsharp",
        "keyword.control.class",
        "keyword.control.clojure",
        "keyword.control.def",
        "keyword.control.fun",
        "keyword.control.function-end.lua",
        "keyword.control.goto.lua",
        "keyword.declaration.dart",
        "keyword.function.go",
        "keyword.local.lua",
        "keyword.operator.macro.dollar.rust",
        "keyword.other.base.cs",
        "keyword.other.declaration-specifier.swift",
        "keyword.other.fn.rust",
        "keyword.other.julia",
        "keyword.other.nim",
        "keyword.other.rust",
        "keyword.other.skinparam.keyword",
        "keyword.other.this.cs",
        "keyword.other.var.cs",
        "markup.bold",
        "markup.deleted.diff",
        "markup.italic",
        "meta.brace.round.ts",
        "meta.class.identifier storage.modifier",
        "meta.embedded.block variable.language punctuation.definition.variable.php",
        "meta.function.powershell storage.type.powershell",
        "meta.macro.rust",
        "meta.separator",
        "punctuation.definition.bold",
        "punctuation.definition.italic",
        "punctuation.definition.ng-binding-name.begin.html",
        "punctuation.definition.ng-binding-name.end.html",
        "punctuation.definition.parameters.begin.ts",
        "punctuation.definition.parameters.end.ts",
        "punctuation.definition.string",
        "punctuation.section.parameters.begin.bracket.round.cpp",
        "punctuation.section.parameters.end.bracket.round.cpp",
        "punctuation.section.parens.begin.bracket.round.cpp",
        "punctuation.section.parens.end.bracket.round.cpp",
        "punctuation.terminator.function",
        "source.go keyword",
        "source.julia storage.modifier",
        "source.ocaml keyword markup.underline",
        "source.ocaml storage.type markup.underline",
        "source.r meta.function.r keyword.control.r",
        "source.scala keyword.declaration",
        "source.tf support.class.variable",
        "source.wsd keyword.other.class",
        "source.wsd keyword.other.linebegin",
        "storage.modifier.static.rust",
        "storage.modifier.super",
        "storage.type",
        "storage.type.alias.go",
        "storage.type.const.go",
        "storage.type.def",
        "storage.type.func.go",
        "storage.type.interface.go",
        "storage.type.type.go",
        "storage.type.var.go",
        "support.type.exception.python",
        "variable.language",
        "variable.language punctuation.definition.variable",
        "variable.parameter.function.language.special"
      ],
      "settings": {
        "foreground": "#b08090"
      }
    },
    {
      "scope": [
        "binding.fsharp keyword",
        "binding.fsharp keyword.symbol",
        "entity.name.function.swift",
        "entity.name.section.fsharp",
        "entity.name.section.fsharp keyword",
        "entity.name.section.latex",
        "keyword.begin.tag.ejs",
        "keyword.control.class",
        "keyword.control.cucumber.table",
        "keyword.control.def",
        "keyword.control.default",
        "keyword.control.directive",
        "keyword.control.function-end.lua",
        "keyword.declaration.dart",
        "keyword.format.specifier.fsharp",
        "keyword.language.gherkin.feature.scenario",
        "keyword.operator.function.infix",
        "keyword.operator.other.powershell",
        "keyword.other.declaration-specifier.swift",
        "keyword.other.julia",
        "keyword.other.nim",
        "keyword.other.rust",
        "keyword.other.skinparam",
        "keyword.other.unit",
        "keyword.other.using.vala",
        "keyword.other.var.cs",
        "keyword.symbol.fsharp",
        "meta.class.identifier storage.modifier",
        "meta.import.haskell keyword",
        "namespace.open.fsharp entity",
        "namespace.open.fsharp keyword",
        "punctuation.definition.variable",
        "record.fsharp keyword",
        "source.apacheconf keyword",
        "source.c keyword.other",
        "source.cpp keyword.other",
        "source.cs keyword.other",
        "source.css keyword.control",
        "source.css keyword.operator",
        "source.css variable.parameter",
        "source.go keyword",
        "source.lua storage.type.function",
        "string.tag.lua",
        "source.nim keyword.other",
        "source.nim keyword.other.common.function",
        "source.objc keyword.other.property.attribute",
        "source.ocaml constant.language constant.numeric entity.other.attribute-name.id.css",
        "source.ocaml keyword markup.underline",
        "source.python meta.function.decorator.python support.type.python",
        "source.reason entity.other.attribute-name constant.language constant.numeric",
        "source.scala entity.name.class.declaration",
        "source.scala keyword.declaration",
        "source.sql keyword.other",
        "source.toml entity.other.attribute-name",
        "source.toml keyword",
        "source.wsd keyword.other",
        "storage.modifier.array.bracket",
        "storage.modifier.import",
        "storage.modifier.package",
        "storage.modifier.static.rust",
        "storage.modifier.using.vala",
        "storage.type",
        "string.interpolated variable.parameter",
        "variable.parameter.handlebars",
        "variable.parameter.r"
      ],
      "settings": {
        "fontStyle": "italic"
      }
    },
    {
      "scope": [
        "binding.fsharp keyword.symbol.fsharp",
        "constant.character",
        "constant.escape",
        "constant.name.attribute.tag.pug",
        "constant.other.description.jsdoc",
        "entity.name.footnote",
        "entity.name.record.field.accessor.elm",
        "entity.name.record.field.elm",
        "entity.other.attribute-name strong",
        "keyword.begin.tag.ejs",
        "keyword.operator.other.powershell",
        "keyword.other.array.phpdoc.php",
        "markup meta punctuation.definition",
        "meta.array.julia",
        "meta.attribute-selector punctuation.definition.entity",
        "meta.bracket.julia",
        "meta.link.inline punctuation.definition.string",
        "punctuation.definition.list_item",
        "punctuation.definition.parameters.begin.lua",
        "punctuation.definition.parameters.finish.lua",
        "punctuation.separator.arguments.lua",
        "punctuation.separator.key-value",
        "source meta.brace",
        "source punctuation",
        "source.clojure meta.symbol",
        "source.css entity.other",
        "source.ocaml entity.name.filename",
        "source.ocaml punctuation.definition.tag",
        "source.reason entity.name.filename",
        "source.sql",
        "storage.modifier.array.bracket",
        "text.html punctuation",
        "text.html.markdown"
      ],
      "settings": {
        "foreground": "#8a8680"
      }
    },
    {
      "scope": [
        "comment",
        "comment.block.documentation punctuation.definition.bracket",
        "comment.line.double-dash.lua",
        "comment.line.shebang.lua",
        "punctuation.definition.comment",
        "punctuation.definition.comment.lua",
        "punctuation.definition.tag",
        "source.ocaml comment constant.regexp meta.separator"
      ],
      "settings": {
        "foreground": "#5a6860"
      }
    },
    {
      "scope": [
        "comment.block.documentation entity.name.type",
        "comment.block.documentation.phpdoc.php keyword.other.type.php",
        "constant.other.reference",
        "constant.other.symbol.hashkey.ruby",
        "constant.other.symbol.hashkey.ruby punctuation.definition.constant.ruby",
        "entity.name.lifetime.rust",
        "entity.name.type.annotation.kotlin",
        "entity.name.type.declaration.rust",
        "entity.name.type.enum.rust",
        "entity.name.type.fsharp",
        "entity.name.type.kotlin",
        "entity.name.type.lifetime.rust",
        "entity.name.type.metavariable.rust",
        "entity.name.type.numeric.rust",
        "entity.name.type.option.rust",
        "entity.name.type.primitive.rust",
        "entity.name.type.result.rust",
        "entity.name.type.rust",
        "entity.name.type.struct.rust",
        "entity.name.type.trait.rust",
        "entity.other.attribute-name.id",
        "entity.other.attribute-name.id punctuation.definition.entity",
        "keyword.type",
        "markup punctuation.definition",
        "meta.type.annotation entity.name.type",
        "meta.type.parameters entity.name.type",
        "punctuation.definition.lifetime.rust",
        "punctuation.definition.storage.type.objc",
        "punctuation.definition.string.begin.html",
        "punctuation.definition.string.end.html",
        "punctuation.definition.typeparameters",
        "punctuation.separator.clause-head-body",
        "source.apex storage.type",
        "source.cpp entity.name.type",
        "source.cpp storage.type.cpp",
        "source.elm storage.type",
        "source.go storage.type",
        "source.graphql support.type",
        "source.groovy storage.type",
        "source.haskell storage.type",
        "source.hlsl storage.type.basic",
        "source.hlsl support.type.other",
        "source.java storage.type",
        "source.nim storage.type",
        "source.python support.type.python",
        "source.reason support.type string",
        "source.scala entity.name.class",
        "source.swift support.type",
        "source.tf meta.keyword.number",
        "source.tf meta.keyword.string",
        "source.vala storage.type",
        "storage.class.std.rust",
        "storage.modifier.lifetime.rust",
        "storage.type.attribute.lua",
        "storage.type.built-in",
        "storage.type.c",
        "storage.type.core.rust",
        "storage.type.cs",
        "storage.type.generic.lua",
        "storage.type.integral",
        "storage.type.objc",
        "storage.type.php",
        "storage.type.powershell",
        "storage.type.primitive",
        "storage.type.r",
        "storage.type.user-defined",
        "string.other.link.title.markdown",
        "support.class.builtin",
        "support.class.crystal",
        "support.type.builtin",
        "support.type.julia",
        "support.type.lua",
        "support.type.primitive",
        "support.type.primitive.ts",
        "support.type.vb",
        "support.variable.property"
      ],
      "settings": {
        "foreground": "#7cc4b8"
      }
    },
    {
      "scope": [
        "constant",
        "constant.character.entity",
        "constant.character.format.placeholder",
        "constant.character.math",
        "constant.other.placeholder",
        "entity.helper.apacheconf",
        "entity.name.function.preprocessor.c",
        "entity.name.tag.html",
        "entity.name.type.type-parameter.cs",
        "entity.other.attribute-name.class",
        "markup.quote",
        "meta.attribute.id entity.other.attribute-name",
        "meta.table.lua variable.other",
        "meta.tag.attributes entity.other.attribute-name",
        "punctuation.bracket.angle",
        "punctuation.definition.constant",
        "punctuation.definition.entity",
        "source.cpp variable.other.enummember",
        "source.cs entity.other.attribute-name",
        "source.graphql constant.character",
        "source.reason constant.language.list",
        "storage.type.module.go",
        "storage.type.scala",
        "support.class.math",
        "support.constant",
        "support.constant punctuation.definition.variable",
        "support.variable.class.hideshow",
        "support.variable.magic",
        "text.html entity.other.attribute-name",
        "text.xml entity.other.attribute-name",
        "variable.language.crystal",
        "variable.other.constant"
      ],
      "settings": {
        "foreground": "#8f704b"
      }
    },
    {
      "scope": [
        "constant.character.escape",
        "constant.character.escape punctuation.definition.keyword",
        "constant.other.haskell",
        "entity.global.clojure",
        "entity.name.class.lua",
        "entity.name.function-table.lua",
        "entity.name.type",
        "entity.name.type.class",
        "entity.namespace.r",
        "entity.other.inherited-class.python",
        "keyword.format.specifier.fsharp",
        "meta.embedded.block.php punctuation.definition.variable.php",
        "meta.embedded.line.crystal punctuation.section.embedded",
        "meta.embedded.line.crystal punctuation.section.embedded source.crystal",
        "meta.method-call.groovy storage.type.groovy",
        "punctuation.definition.interpolation",
        "punctuation.definition.template-expression",
        "punctuation.section.embedded",
        "punctuation.section.embedded source.swift",
        "punctuation.section.embedded.begin.ruby",
        "punctuation.section.embedded.end.ruby source.ruby",
        "punctuation.section.tag",
        "source.clojure punctuation.section.metadata",
        "source.clojure punctuation.section.set",
        "source.js constant.other.object.key.js string.unquoted.label.js",
        "source.js punctuation.section.embedded",
        "source.objc entity.name.tag",
        "source.ocaml entity.name.class constant.numeric",
        "source.python meta.function-call.python support.type.python",
        "source.reason entity.name.class",
        "source.scala entity.name.class.declaration",
        "source.tf meta.keyword.list",
        "source.tf meta.keyword.map",
        "source.vala storage.type",
        "storage.modifier.using.vala",
        "storage.type.string.python",
        "string.interpolated.dollar punctuation.definition.string",
        "string.interpolated.pug",
        "string.quoted.other.literal.upper.crystal punctuation.definition.string",
        "string.replacement.apacheconf",
        "support.class",
        "support.class.lua",
        "support.constant.handlebars",
        "support.constant.math",
        "support.function.macro.julia",
        "support.module.elm",
        "support.variable.class.group",
        "support.variable.lua",
        "variable.other.bracket punctuation.definition.variable"
      ],
      "settings": {
        "foreground": "#4d9e9b",
        "fontStyle": "bold"
      }
    },
    {
      "scope": [
        "constant.character.escape.backslash.rust",
        "constant.character.escape.bit.rust",
        "constant.character.escape.byte.lua",
        "constant.character.escape.lua",
        "constant.character.escape.rust",
        "constant.character.escape.unicode.lua",
        "constant.character.escape.unicode.punctuation.rust",
        "constant.character.escape.unicode.rust"
      ],
      "settings": {
        "foreground": "#e8b878",
        "fontStyle": "bold"
      }
    },
    {
      "scope": [
        "constant.character.literal.scala",
        "constant.language.boolean.false.ts",
        "constant.language.boolean.true.ts",
        "constant.language.dart",
        "constant.numeric.dart",
        "constant.numeric.decimal.cpp",
        "constant.numeric.decimal.ts",
        "entity.name.import.go",
        "entity.name.type.module.go",
        "markup.inline.raw punctuation.definition.raw",
        "markup.inline.raw.string",
        "markup.inserted.diff",
        "markup.raw.texttt",
        "punctuation.definition.string.begin.lua",
        "punctuation.definition.string.begin.ts",
        "punctuation.definition.string.end.lua",
        "punctuation.definition.string.end.ts",
        "punctuation.definition.string.template",
        "source.css support.constant",
        "source.scala punctuation.definition.character",
        "source.tf entity.name",
        "string",
        "string.interpolated.python string.quoted.single.python",
        "string.quoted.double.heredoc",
        "string.quoted.double.interpolated.crystal",
        "string.quoted.double.interpolated.crystal punctuation.definition.string",
        "string.quoted.double.lua",
        "string.quoted.interpolated.vala",
        "string.quoted.interpolated.vala punctuation.definition.string",
        "string.quoted.other.multiline.lua",
        "string.quoted.single.lua",
        "string.regexp.apacheconf",
        "string.template",
        "text.html.derivative",
        "text.tex markup.raw",
        "variable.other.constant.ts"
      ],
      "settings": {
        "foreground": "#c9856a"
      }
    },
    {
      "scope": [
        "constant.integer.apacheconf",
        "constant.language",
        "constant.language.lua",
        "constant.language punctuation.definition.variable",
        "constant.numeric",
        "constant.numeric.float.hexadecimal.lua",
        "constant.numeric.float.lua",
        "constant.numeric.integer.hexadecimal.lua",
        "constant.numeric.integer.lua",
        "constant.others.fsharp",
        "keyword.operator.null-conditional.cs",
        "keyword.operator.nullable-type",
        "keyword.other.unit",
        "markup.inline.raw.string.markdown",
        "punctuation.separator.decimal.period.php",
        "punctuation.separator.question-mark.cs",
        "source.toml constant",
        "string.quoted.double.skinparam.value"
      ],
      "settings": {
        "foreground": "#d4a054"
      }
    },
    {
      "scope": [
        "constant.language.bool.rust",
        "constant.numeric.bin.rust",
        "constant.numeric.decimal.exponent.mantissa.rust",
        "constant.numeric.decimal.rust",
        "constant.numeric.hex.rust",
        "constant.numeric.oct.rust",
        "constant.other.caps.rust",
        "punctuation.separator.dot.decimal.rust"
      ],
      "settings": {
        "foreground": "#d4a054"
      }
    },
    {
      "scope": [
        "constant.language.unit.fsharp",
        "entity.mime-type.apacheconf",
        "entity.name",
        "entity.name.function.call.kotlin",
        "entity.name.function.infix",
        "entity.name.module.rust",
        "entity.name.namespace.rust",
        "entity.name.scope-resolution.function.call",
        "entity.name.type.namespace",
        "entity.other",
        "entity.other.attribute-name.html",
        "entity.other.ng-binding-name.template.html",
        "keyword.language.gherkin.feature.scenario",
        "keyword.operator.function.infix",
        "markup.changed.git_gutter",
        "markup.underline",
        "meta.import.rust",
        "meta.symbol.namespace.clojure",
        "meta.use.php",
        "meta.use.rust",
        "punctuation.definition.parameters",
        "source.nim keyword.other.common.function",
        "source.ocaml constant.language constant.numeric entity.other.attribute-name.id.css",
        "source.reason constant.language.unit",
        "source.reason entity.other.attribute-name constant.language constant.numeric",
        "source.wsd support.class.preprocessings",
        "support.class",
        "support.function",
        "support.function.construct",
        "support.orther.namespace.use.php",
        "support.other.namespace.php",
        "support.type",
        "text.tex support.function.texttt",
        "text.tex support.function.verb"
      ],
      "settings": {
        "foreground": "#8a80a8"
      }
    },
    {
      "scope": [
        "constant.other.color",
        "constant.string.documentation.powershell",
        "entity.name.section",
        "entity.other.attribute-name.pseudo-class",
        "entity.other.attribute-name.pseudo-class.css punctuation.definition.entity.css",
        "entity.other.attribute-name.pseudo-element",
        "entity.other.attribute-name.pseudo-element.css punctuation.definition.entity.css",
        "keyword",
        "keyword.control",
        "keyword.control.lua",
        "keyword.control punctuation.definition.function",
        "keyword.control.class.ruby",
        "keyword.control.def.ruby",
        "keyword.import",
        "keyword.operator.lua",
        "keyword.other.class.fileds",
        "keyword.other.substitution",
        "keyword.other.template",
        "keyword.package",
        "markup.heading",
        "markup.heading punctuation.definition",
        "meta.expression.clojure",
        "meta.tag.sgml",
        "punctuation.accessor",
        "punctuation.definition.attribute",
        "punctuation.definition.directive",
        "punctuation.definition.keyword",
        "punctuation.definition.parameters.varargs",
        "punctuation.definition.preprocessor",
        "punctuation.section.directive",
        "punctuation.separator.hash.cs",
        "punctuation.separator.method",
        "punctuation.separator.namespace",
        "punctuation.separator.other.ruby",
        "punctuation.separator.pointer-access",
        "punctuation.separator.question-mark.cs",
        "punctuation.separator.slice.python",
        "sharing.modifier",
        "source.clojure storage.control",
        "source.go keyword.operator",
        "source.kotlin storage.type.import",
        "source.kotlin storage.type.package",
        "source.ocaml variable.interpolation string",
        "source.reason variable.interpolation",
        "source.toml entity.other.attribute-name",
        "storage.modifier",
        "storage.type.function.pug",
        "storage.type.modifier",
        "storage.type.rust",
        "tag.decorator.js entity.name.tag.js",
        "tag.decorator.js punctuation.definition.tag.js",
        "text.pug meta.tag.other",
        "text.pug storage.type",
        "variable.parameter.rest.lua"
      ],
      "settings": {
        "foreground": "#daae6d"
      }
    },
    {
      "scope": [
        "constant.other.color",
        "constant.other.symbol.hashkey.ruby punctuation.definition.constant.ruby",
        "constant.other.symbol.ruby punctuation.definition.constant.ruby",
        "constant.other.symbol.ruby punctuation.definition.constant.ruby",
        "entity.name.function.definition.special.constructor",
        "entity.name.function.definition.special.member.destructor.",
        "entity.name.section",
        "entity.name.type.annotation.kotlin",
        "entity.name.variable.parameter",
        "keyword",
        "keyword.control",
        "keyword.control.class.ruby",
        "keyword.control.def.ruby",
        "keyword.operator",
        "keyword.other.new",
        "keyword.other.substitution",
        "keyword.other.template",
        "markdown.heading",
        "markup punctuation.definition",
        "markup.bold",
        "markup.bold string",
        "markup.heading",
        "markup.inline.raw punctuation.definition.raw",
        "meta.function.parameters variable punctuation.definition.variable.php",
        "meta.function.parameters variable.other",
        "parameter.variable.function",
        "punctuation.accessor",
        "punctuation.bracket.angle",
        "punctuation.definition.preprocessor",
        "punctuation.section.directive",
        "punctuation.separator.hash.cs",
        "punctuation.separator.method",
        "punctuation.separator.namespace",
        "punctuation.separator.question-mark.cs",
        "source.go keyword.operator",
        "source.graphql support.type.builtin",
        "source.ocaml variable.interpolation string",
        "source.ruby punctuation.definition.variable",
        "source.wsd keyword.other.activity",
        "storage.type.annotation",
        "storage.type.function.arrow",
        "storage.type.function.coffee",
        "storage.type.function.pug",
        "storage.type.function.python",
        "storage.type.generic.wildcard",
        "storage.type.objc",
        "support.function.builtin.rust",
        "support.function.textbf",
        "variable.parameter",
        "variable.parameter.function.lua"
      ],
      "settings": {
        "fontStyle": "bold"
      }
    },
    {
      "scope": [
        "constant.other.placeholder"
      ],
      "settings": {
        "foreground": "#c9856a"
      }
    },
    {
      "scope": [
        "entity.name.function",
        "entity.name.function.lua",
        "entity.name.function.rust",
        "entity.name.section.fsharp entity.name.section.fsharp",
        "keyword.control.cucumber.table",
        "markup.link",
        "markup.underline.link",
        "markup.underline.link.image",
        "meta.class.body.groovy meta.method.body.java storage.type.groovy",
        "meta.function-call.generic.python",
        "meta.function.call.rust",
        "meta.function.definition.rust",
        "meta.method-call.groovy meta.method.groovy",
        "punctuation.decorator",
        "punctuation.definition.decorator",
        "source.tf support.class",
        "string.other.link",
        "support.function.any-method",
        "support.function.any-method.lua",
        "support.function.go",
        "support.function.library.lua",
        "support.function.lua",
        "support.other.variable",
        "support.type.property-name",
        "support.type.vendored",
        "support.variable.class.function",
        "text.tex punctuation.definition.function",
        "text.tex support.function",
        "variable.function"
      ],
      "settings": {
        "foreground": "#89e3f6"
      }
    },
    {
      "scope": [
        "entity.name.lifetime.rust",
        "keyword.other.fn.rust",
        "markup.bold markup.italic",
        "markup.bold markup.italic string",
        "markup.italic markup.bold",
        "markup.italic markup.bold string",
        "markup.quote markup.bold",
        "markup.quote markup.bold string",
        "meta.attribute.id entity.other.attribute-name",
        "source.ocaml punctuation.definition.tag emphasis",
        "source.rust meta.attribute.rust",
        "source.tf entity.name",
        "storage.modifier.lifetime.rust",
        "text.html punctuation.section.embedded",
        "variable.other.c"
      ],
      "settings": {
        "fontStyle": "bold italic"
      }
    },
    {
      "scope": [
        "entity.name.module",
        "entity.name.package.go",
        "entity.name.package.kotlin",
        "entity.name.variable",
        "markup.list",
        "meta.embedded.block variable punctuation.definition.variable.php",
        "meta.function-call.arguments.python",
        "meta.template.expression.kotlin",
        "meta.toc-list.id.html",
        "meta.var.clojure",
        "parameter.variable.function",
        "punctuation.definition.annotation",
        "punctuation.definition.placeholder",
        "punctuation.definition.variable",
        "source.apacheconf",
        "source.c",
        "source.coffee",
        "source.coffee.embedded.source",
        "source.cpp",
        "source.crystal",
        "source.css entity.name.tag.custom",
        "source.elixir.embedded.source",
        "source.elm meta.declaration.module",
        "source.elm meta.value",
        "source.go",
        "source.groovy.embedded.source",
        "source.java meta.class.body.java",
        "source.json meta.structure.dictionary.json support.type.property-name.json",
        "source.julia",
        "source.objc",
        "source.powershell",
        "source.python",
        "source.reason variable.language",
        "source.reason variable.language string.other.link",
        "source.ruby",
        "source.scala entity.name.import",
        "source.shell",
        "source.sql.embedded",
        "source.swift",
        "source.tf meta.template.expression",
        "source.toml keyword",
        "storage.modifier.import",
        "storage.modifier.package",
        "storage.type.annotation",
        "string.quoted.double.class.other",
        "string.quoted.double.kotlin entity.string.template.element.kotlin",
        "string.quoted.interpolated.vala constant.character.escape.vala",
        "support",
        "support.type.nim",
        "variable",
        "variable.import.parameter",
        "variable.object",
        "variable.other",
        "variable.other.class",
        "variable.other.constant.elixir",
        "variable.other.lua",
        "variable.other.normal punctuation.definition.variable.shell",
        "variable.parameter"
      ],
      "settings": {
        "foreground": "#4d9e9b"
      }
    },
    {
      "scope": [
        "invalid",
        "invalid.illegal",
        "invalid.illegal.character.escape.lua",
        "invalid.illegal.unrecognized-string-escape.zig"
      ],
      "settings": {
        "foreground": "#3a4240",
        "fontStyle": "strikethrough"
      }
    },
    {
      "scope": [
        "comment.line.documentation.zig",
        "comment.line.double-slash.zig"
      ],
      "settings": {
        "foreground": "#5a6860",
        "fontStyle": "italic"
      }
    },
    {
      "scope": [
        "keyword.todo.zig"
      ],
      "settings": {
        "foreground": "#daae6d",
        "fontStyle": "bold"
      }
    },
    {
      "scope": [
        "keyword.storage.zig",
        "keyword.structure.zig",
        "keyword.statement.zig",
        "keyword.control.flow.zig",
        "keyword.control.async.zig",
        "keyword.control.trycatch.zig",
        "keyword.control.conditional.zig",
        "keyword.control.repeat.zig",
        "keyword.default.zig"
      ],
      "settings": {
        "foreground": "#daae6d",
        "fontStyle": "bold"
      }
    },
    {
      "scope": [
        "keyword.constant.default.zig",
        "keyword.constant.bool.zig"
      ],
      "settings": {
        "foreground": "#8f704b"
      }
    },
    {
      "scope": [
        "keyword.type.zig",
        "keyword.type.integer.zig",
        "keyword.type.c.zig"
      ],
      "settings": {
        "foreground": "#7cc4b8"
      }
    },
    {
      "scope": [
        "storage.type.function.zig"
      ],
      "settings": {
        "foreground": "#b08090",
        "fontStyle": "bold"
      }
    },
    {
      "scope": [
        "entity.name.function.zig",
        "entity.name.function.string.zig"
      ],
      "settings": {
        "foreground": "#89e3f6"
      }
    },
    {
      "scope": [
        "entity.name.type.zig"
      ],
      "settings": {
        "foreground": "#4d9e9b",
        "fontStyle": "bold"
      }
    },
    {
      "scope": [
        "variable.zig",
        "variable.string.zig"
      ],
      "settings": {
        "foreground": "#4d9e9b"
      }
    },
    {
      "scope": [
        "support.function.builtin.zig"
      ],
      "settings": {
        "foreground": "#d4a060",
        "fontStyle": "bold"
      }
    },
    {
      "scope": [
        "string.quoted.double.zig",
        "string.multiline.zig",
        "string.quoted.single.zig"
      ],
      "settings": {
        "foreground": "#c9856a"
      }
    },
    {
      "scope": [
        "constant.character.escape.zig"
      ],
      "settings": {
        "foreground": "#e8b878",
        "fontStyle": "bold"
      }
    },
    {
      "scope": [
        "constant.numeric.hexfloat.zig",
        "constant.numeric.float.zig",
        "constant.numeric.decimal.zig",
        "constant.numeric.hexadecimal.zig",
        "constant.numeric.octal.zig",
        "constant.numeric.binary.zig"
      ],
      "settings": {
        "foreground": "#d4a054"
      }
    },
    {
      "scope": [
        "constant.numeric.invalid.zig"
      ],
      "settings": {
        "foreground": "#3a4240",
        "fontStyle": "strikethrough"
      }
    },
    {
      "scope": [
        "keyword.operator.c-pointer.zig",
        "keyword.operator.comparison.zig",
        "keyword.operator.arithmetic.zig",
        "keyword.operator.bitwise.zig",
        "keyword.operator.special.zig",
        "keyword.operator.assignment.zig",
        "keyword.operator.question.zig"
      ],
      "settings": {
        "foreground": "#daae6d",
        "fontStyle": "bold"
      }
    },
    {
      "scope": [
        "punctuation.accessor.zig",
        "punctuation.comma.zig",
        "punctuation.separator.key-value.zig",
        "punctuation.terminator.statement.zig"
      ],
      "settings": {
        "foreground": "#8a8680"
      }
    },
    {
      "scope": [
        "keyword.control.rust",
        "keyword.operator.access.dot.rust",
        "keyword.operator.arrow.fat.rust",
        "keyword.operator.arrow.skinny.rust",
        "keyword.operator.assignment.equal.rust",
        "keyword.operator.assignment.rust",
        "keyword.operator.borrow.and.rust",
        "keyword.operator.borrow.rust",
        "keyword.operator.comparison.rust",
        "keyword.operator.dereference.rust",
        "keyword.operator.exponent.rust",
        "keyword.operator.exponent.sign.rust",
        "keyword.operator.key-value.rust",
        "keyword.operator.logical.rust",
        "keyword.operator.math.rust",
        "keyword.operator.namespace.rust",
        "keyword.operator.question.rust",
        "keyword.operator.range.rust",
        "keyword.operator.subpattern.rust",
        "keyword.other.crate.rust"
      ],
      "settings": {
        "foreground": "#daae6d"
      }
    },
    {
      "scope": [
        "entity.name.variable.lua",
        "meta.attribute.rust",
        "punctuation.brackets.attribute.rust",
        "punctuation.definition.attribute.rust",
        "storage.type.annotation.lua"
      ],
      "settings": {
        "foreground": "#d4a060"
      }
    },
    {
      "scope": [
        "meta.interpolation.rust",
        "punctuation.brackets.angle.rust",
        "punctuation.brackets.curly.rust",
        "punctuation.brackets.round.rust",
        "punctuation.brackets.square.rust",
        "punctuation.comma.rust",
        "punctuation.definition.interpolation.rust",
        "punctuation.semi.rust"
      ],
      "settings": {
        "foreground": "#8a8680"
      }
    },
    {
      "scope": [
        "punctuation.definition.char.rust",
        "punctuation.definition.string.raw.rust",
        "punctuation.definition.string.rust",
        "string.quoted.byte.raw.rust",
        "string.quoted.double.rust",
        "string.quoted.single.char.rust"
      ],
      "settings": {
        "foreground": "#c9856a"
      }
    },
    {
      "scope": [
        "entity.other.attribute.lua",
        "punctuation.definition.typeparameters.begin.ts",
        "punctuation.definition.typeparameters.end.ts",
        "variable.other.property"
      ],
      "settings": {
        "foreground": "#6eb8b0",
        "fontStyle": ""
      }
    },
    {
      "scope": [
        "source.dart",
        "source.go",
        "source.ts",
        "string.quoted.double.html",
        "variable.field.go"
      ],
      "settings": {
        "foreground": "#b8b4ac",
        "fontStyle": ""
      }
    },
    {
      "scope": [
        "support.class.console.ts",
        "support.function.console.ts"
      ],
      "settings": {
        "foreground": "#daae6d",
        "fontStyle": "bold underline"
      }
    },
    {
      "scope": [
        "token.debug-token"
      ],
      "settings": {
        "foreground": "#4d9e9b",
        "fontStyle": "bold"
      }
    },
    {
      "scope": [
        "token.error-token"
      ],
      "settings": {
        "foreground": "#c45a4a"
      }
    },
    {
      "scope": [
        "token.info-token"
      ],
      "settings": {
        "foreground": "#89e3f6"
      }
    },
    {
      "scope": [
        "token.warn-token"
      ],
      "settings": {
        "foreground": "#d4a054"
      }
    },
    {
      "scope": [
        "variable.language.self.lua",
        "variable.language.self.rust",
        "variable.language.super.rust",
        "variable.other.metavariable.name.rust",
        "variable.other.metavariable.specifier.rust",
        "variable.other.rust"
      ],
      "settings": {
        "foreground": "#4d9e9b"
      }
    }
  ]
}